bassist/__init__.py
bassist/__main__.py
bassist/backup.py
bassist/cli.py
bassist/compact.py
bassist/config.py
bassist/quota.py
bassist/report.py
bassist/util.py
bassist-1.2.dist-info/LICENSE
bassist-1.2.dist-info/METADATA
bassist-1.2.dist-info/WHEEL
bassist-1.2.dist-info/entry_points.txt
bassist-1.2.dist-info/top_level.txt
bassist-1.2.dist-info/RECORD
